nbdev_intgrt/__init__.py
nbdev_intgrt/_modidx.py
nbdev_intgrt/core.py
nbdev_intgrt/intgrt.py
nbdev_intgrt-1.0.1.dist-info/LICENSE
nbdev_intgrt-1.0.1.dist-info/METADATA
nbdev_intgrt-1.0.1.dist-info/WHEEL
nbdev_intgrt-1.0.1.dist-info/entry_points.txt
nbdev_intgrt-1.0.1.dist-info/top_level.txt
nbdev_intgrt-1.0.1.dist-info/RECORD
