Metadata-Version: 2.1
Name: nbdev-intgrt
Version: 1.0.1
Summary: a project that implements numeric integration
Home-page: https://github.com/rbagdazian/nbdev-intgrt
Author: rbagdazian
Author-email: rbagdazian@gmail.com
License: Apache Software License 2.0
Keywords: nbdev jupyter notebook python
Classifier: Development Status :: 4 - Beta
Classifier: Intended Audience :: Developers
Classifier: Natural Language :: English
Classifier: Programming Language :: Python :: 3.7
Classifier: Programming Language :: Python :: 3.8
Classifier: Programming Language :: Python :: 3.9
Classifier: Programming Language :: Python :: 3.10
Classifier: License :: OSI Approved :: Apache Software License
Requires-Python: >=3.7
License-File: LICENSE
Provides-Extra: dev
